{
  "url": "https://www.loom.com/share/6c700c3a6ba54aeaa9d5f92b5927438f",
  "type": "video",
  "processed_at": "2026-01-22T12:50:04.833556",
  "content": "はい、画像について説明します。\nこの画像は、画面をキャプチャしたものです。動画のタイトルは「インスタでの成功への道と心構え」で、著者は祐菜 下田で、12日前に共有されました。動画のビュー数は6回です。動画の下には、ユーザーがリアクションを残すことができるセクションがあります。また、動画の右側にはアクティビティのタブとトランスクリプトのタブが表示されています。アクティビティのタブの下には、ユーザーがコメントを書き込むことができるセクションがあります。現在のところ、コメントはまだありません。動画の画面キャプチャには、ディスコードのチャンネル、ゆなチームとおはな講師の会話が含まれています。会話は、インスタの投稿を作成するためのヒントや戦略に焦点を当てています。動画は、インスタグラムで成功したいと思っている人向けのハウツーチュートリアルのようです。\nここに表示されているすべてのテキストの書き起こしです。\n*Loom\nインスタでの成功への道と心構え\n祐菜 下田 12 days ago\nLearn to Loom\nHow to Record\nLoom Blog\nPricing\nLog in\nGet Loom free\nActivity Transcript\n6 views山\nDiscord Edit View Window Help\n01月10日(土) 11:25\n株式会社Levela\n株式会社Level\n#ゆなチーム・おはな講師\n株式会社検索\nQ\nりょうすけ調\n●【】おはな@recipe_chara クリックして原付ファイルを表示\nあき調師\n【講師MG】 ゆな 154\nこれでいきましょう!\nオンライン\nkoki komal\n違ょん講師\nおさくパパ\n●[MG] ゆな これでいきましょう!\n【講師】おはな@recipe_ohana 3:4\nなび(Excel) 講師\n@【講師MG】ゆな\nありがとうございます\nなち講師\nゆり講師\nミク講師\nジムのすけ講師\nにに夫婦講師\n#ゆなチーム\nゆりな講師\nおはな調\nフミ講師\nじゅんママ講\n「新柄と努力すごいと思います\n【講師】おはな@recipe chans 366\nAT\n思ってたし\nインスタンス\n[CS] はるな(ふるはる)\n■【講師/CS] みおな@mi..\n【講師MG】ゆな\n●【講師】 おはな@recipe...\n●【講師教育MG] いけち\n【講師教育MG] はむ@...\n【講師教育MG】ポム\n●【购回秘書】 みづき」\nオフライン-22\n[COO] なぎ\n[CS/マーケ】りお\n(ゆきの)\n33 はい、えーと、お花さんお疲れ様です。えーと、ここに関してちょっとふわ\n•\nっとしてるのがもったいないかなと思います。\n件の新しいメンション\n【講師】おはな@recipe_ohana に返信中\n【MG】ゆ\n+ “おはな講師へメッセージを送信\nON\n● [CS] みゆう\n[CS] ゆうか\nComment\nRespond to 祐菜...\nNo comments... yet\nHit C to reply to 祐菜.",
  "title": "動画コンテンツ",
  "error": null
}