{
  "url": "https://www.instagram.com/rika_aus_/",
  "type": "video",
  "processed_at": "2026-01-22T13:06:37.428433",
  "content": "はい、承知いたしました。この画像の内容を説明します。\n\n**画像の内容**\n\nこの画像は、Instagramのウェブサイトまたはアプリでプロフィールが見つからない場合に表示される画面です。\n\n*   **上部**: Instagramのロゴと「Log in」のリンクがあります。\n*   **中央**: エラーアイコンとともに、「Profile isn't available」というテキストが表示されています。その下に「The link may be broken, or the profile may have been removed.」という説明文があります。\n*   **ボタン**: 「Sign up for Instagram」という青色のボタンがあります。\n*   **下部**: 「By continuing, you agree to Instagram's Terms of Use and Privacy Policy.」というテキストが表示され、利用規約とプライバシーポリシーに同意することを意味します。\n\n**テキストの書き起こし**\n\n*   Instagram\n*   Profile isn't available\n*   The link may be broken, or the profile may have been removed.\n*   Sign up for Instagram\n*   Log in\n*   X By continuing, you agree to Instagram's Terms of Use and Privacy Policy.\n\nこの情報でよろしいでしょうか？",
  "title": "動画コンテンツ",
  "error": null
}