{
  "url": "https://www.instagram.com/haru_dietgohan/",
  "type": "video",
  "processed_at": "2026-01-23T06:37:48.488416",
  "content": "ご提示いただいたURL `https://www.instagram.com/haru_dietgohan/` から分かる情報は以下の通りです。\n\n1.  **プラットフォーム (Platform):**\n    *   `instagram.com` というドメインから、このURLは**Instagram (インスタグラム)** のコンテンツであることが明確に分かります。\n\n2.  **コンテンツの種類 (Type of Content):**\n    *   ドメイン名の直後にスラッシュとユーザー名が続いている形式であるため、これは特定の投稿ではなく、**Instagramユーザーのプロフィールページ（アカウントページ）** を指しています。\n\n3.  **ID/ユーザー名 (ID/Username):**\n    *   URLの最後の部分である `haru_dietgohan` が、このInstagramアカウントの**ユーザー名（またはハンドル名）** です。この名前が、Instagram上でこのプロフィールを一意に識別するためのIDとなります。\n\n4.  **推測されるコンテンツのテーマ:**\n    *   ユーザー名が「haru_dietgohan」であることから、アカウントの主な内容は「ダイエット食」「健康的な食事」「レシピ」「食事記録」など、**食とダイエットに関連する情報** を発信している可能性が高いと推測できます。\n\n**まとめ:**\n\nこのURLは、写真・動画共有ソーシャルメディアである**Instagram** における「**haru_dietgohan**」というユーザーの**プロフィールページ** を示しています。ページにアクセスすると、このユーザーが投稿した写真や動画、リール、ストーリーズ、自己紹介文などを見ることができます。ユーザー名から、食とダイエットに関するコンテンツが主なテーマであると推測されます。",
  "title": "",
  "error": null
}