{
  "id": "20cf3b0f-ba85-80f3-9602-c74c523314a9",
  "title": "チームセッションについて要望があります。チームセッションの目的は、生徒の自主性や積極性を伸ばすためとあり、生徒の任意に任されてますが。最近、チームセッションでトラブルありました。私のチームセッション らむちゃんb組-1では、私以外の方が最初に司会交代の話しをしても、代わりにやろうとする人が出ず、私が毎回司会と日程調整をしてました。ですが、日程調整の連絡しても、リアクションや返信こないことが多々ありました。それで、当日非開催という形に。それまでの連絡の手間やリマインドなども行ったりしてるので、当日非開催になると非効率だし、労力がかかってます。正直、そんな時間を無駄にするより、自分の投稿作りの時間や勉強会の時間に回したいと思ってしまいます。オン会で聞いたのですが、先輩達はチームセッションがなかったとのことで、私としてはチームセッション無くしてもいいと思います。やる気のある人は、自分から交流会やオン会などいろいろなとこに顔出して参加します。私もですが、自分から情報収集に行っている方が多いです。無くすのが難しいようであれば、強制ではなくやりたい人だけやってくださいみたいな、任意性ががいいのではないでしょうか。もしかすると、私のチームセッション メンバー内で起こってる事象かもしれないですが、一度企画の見直しをお願いいたします。",
  "type": "page",
  "created_time": "",
  "last_edited_time": "",
  "url": "",
  "synced_at": "2026-01-21T19:05:29.623208"
}