{
  "page_id": "29ff3b0f-ba85-8080-adf2-e549f13f002c",
  "created_time": "2025-11-02T15:31:00.000Z",
  "last_edited_time": "2025-11-03T10:15:00.000Z",
  "url": "https://www.notion.so/29ff3b0fba858080adf2e549f13f002c",
  "properties": {
    "タイミング": {"type": "select", "select": {"name": "クラス案内前", "color": "pink"}},
    "発生時期": {"type": "date", "date": {"start": "2025-10-31"}},
    "入学式": {"type": "select", "select": {"name": "予約前", "color": "yellow"}},
    "月": {"type": "multi_select", "multi_select": [{"name": "10月"}]},
    "運営LINE URL": {"type": "url", "url": "https://manager.linestep.net/line/detail/222220028"},
    "クラス": {"type": "rich_text", "rich_text": []},
    "トラブルカテゴリ": {"type": "select", "select": {"name": "自信なし", "color": "gray"}},
    "選択": {"type": "select", "select": {"name": "西岡駿", "color": "orange"}},
    "名前と理由": {"id": "title", "type": "title", "title": [{"plain_text": "まつだかおり"}]}
  }
}
