{
  "id": "2cdf3b0f-ba85-8085-afdd-e85bbd8487e5",
  "title": "┗募集案内Notion作成",
  "created_time": "2025-12-18T11:35:00.000Z",
  "last_edited_time": "2025-12-20T15:47:00.000Z",
  "url": "https://www.notion.so/Notion-2cdf3b0fba858085afdde85bbd8487e5",
  "properties": {
    "備考": {
      "id": "XM%3Al",
      "type": "rich_text",
      "rich_text": []
    },
    "ユーザー": {
      "id": "ev%40%3A",
      "type": "people",
      "people": []
    },
    "期日": {
      "id": "xZmF",
      "type": "url",
      "url": null
    },
    "タスク": {
      "id": "title",
      "type": "title",
      "title": [
        {
          "type": "text",
          "text": {
            "content": "┗募集案内Notion作成",
            "link": null
          },
          "annotations": {
            "bold": false,
            "italic": false,
            "strikethrough": false,
            "underline": false,
            "code": false,
            "color": "default"
          },
          "plain_text": "┗募集案内Notion作成",
          "href": null
        }
      ]
    }
  }
}